LICENSE.pdf
MANIFEST.in
README.md
pyproject.toml
setup.cfg
setup.py
freebarcodes/FreeDivSphere.py
freebarcodes/__init__.py
freebarcodes/concatenate.py
freebarcodes/config.py
freebarcodes/decode.py
freebarcodes/editmeasures.c
freebarcodes/editmeasures.pyx
freebarcodes/generate.py
freebarcodes/main.py
freebarcodes/prune.py
freebarcodes/seqiters.py
freebarcodes/seqtools.py
freebarcodes.egg-info/PKG-INFO
freebarcodes.egg-info/SOURCES.txt
freebarcodes.egg-info/dependency_links.txt
freebarcodes.egg-info/entry_points.txt
freebarcodes.egg-info/not-zip-safe
freebarcodes.egg-info/requires.txt
freebarcodes.egg-info/top_level.txt